LICENSE
tabulate_django/__init__.py
tabulate_django-0.3.0.dist-info/LICENSE
tabulate_django-0.3.0.dist-info/METADATA
tabulate_django-0.3.0.dist-info/WHEEL
tabulate_django-0.3.0.dist-info/RECORD
